ahp_calculator/__init__.py
ahp_calculator/ahp_calculator.py
ahp_calculator/constants.py
ahp_calculator/helper.py
ahp_calculator-0.3.0.dist-info/LICENSE
ahp_calculator-0.3.0.dist-info/METADATA
ahp_calculator-0.3.0.dist-info/WHEEL
ahp_calculator-0.3.0.dist-info/top_level.txt
ahp_calculator-0.3.0.dist-info/RECORD
