Metadata-Version: 2.1
Name: ahp-calculator
Version: 0.3.0
Summary: AHP is one of the extensively used Multi Criteria Decision Making (MCDM) tool for processing multiple important objectives and weighting the criteria. The AHP allows to assign a priority among various alternatives and integrating multidimensional measures into a single scale of priorities.
Home-page: https://github.com/Geospasolutions/AHP_Calculator/
Author: Rohit Gautam, Prashant Thapaliya, Binabh Devkota
Author-email: rowheat02@gmail.com
License: LICENSE
Platform: UNKNOWN
License-File: LICENSE
Requires-Dist: ipywidgets (==7.6.5)
Requires-Dist: numpy (==1.20.3)
